{
  "$schema": "../gen/schemas/desktop-schema.json",
  "identifier": "default",
  "description": "Main window — chrome controls + loopback gzTau UI IPC",
  "windows": ["main"],
  "remote": {
    "urls": ["http://127.0.0.1:*", "http://localhost:*"]
  },
  "permissions": [
    "core:default",
    "core:webview:allow-set-webview-focus",
    "core:window:allow-set-focus",
    "core:window:allow-show",
    "core:window:allow-hide",
    "core:window:allow-unminimize",
    "core:window:allow-minimize",
    "core:window:allow-maximize",
    "core:window:allow-unmaximize",
    "core:window:allow-toggle-maximize",
    "core:window:allow-close",
    "core:window:allow-set-icon",
    "core:window:allow-is-maximized",
    "core:window:allow-start-dragging",
    "core:path:default",
    "core:event:default",
    "allow-app-commands"
  ]
}
